asgarde/__init__.py
asgarde/collection_composer.py
asgarde/failure.py
asgarde/tests/__init__.py
asgarde/tests/player.py
asgarde/tests/team.py
asgarde/tests/test_collection_composer.py
asgarde/tests/testing_helper.py
asgarde/transforms/__init__.py
asgarde/transforms/do_fns_error_handling.py
asgarde-0.16.0.dist-info/LICENSE
asgarde-0.16.0.dist-info/METADATA
asgarde-0.16.0.dist-info/WHEEL
asgarde-0.16.0.dist-info/top_level.txt
asgarde-0.16.0.dist-info/RECORD
