Metadata-Version: 2.1
Name: asgarde
Version: 0.16.0
Summary: Allows simplifying error handling with Apache Beam
Home-page: https://github.com/tosun-si/pasgarde
Author: Mazlum TOSUN
Author-email: mazlum.tosun@gmail.com
License: UNKNOWN
Platform: UNKNOWN
Classifier: License :: OSI Approved :: MIT License
Classifier: Programming Language :: Python :: 3
Classifier: Operating System :: OS Independent
Requires-Python: >=3.6.10
